bluepy_devices/__init__.py
bluepy_devices/lib/connection.py
bluepy_devices/lib/__init__.py
bluepy_devices/devices/eq3btsmart.py
bluepy_devices/devices/__init__.py
bluepy_devices-0.1.dist-info/DESCRIPTION.rst
bluepy_devices-0.1.dist-info/RECORD
bluepy_devices-0.1.dist-info/WHEEL
bluepy_devices-0.1.dist-info/top_level.txt
bluepy_devices-0.1.dist-info/METADATA
bluepy_devices-0.1.dist-info/metadata.json
