Metadata-Version: 2.0
Name: bluepy-devices
Version: 0.1
Summary: Usability Library for bluepy, and device implementations, mainly for homeassistant integration
Home-page: https://github.com/bimbar/bluepy_devices.git
Author: Markus Peter
Author-email: mpeter@emdev.de
License: MIT
Platform: UNKNOWN
Requires-Dist: bluepy (>=1.0.4)
